pyfieldlib/__init__.py
pyfieldlib-1.0.1.dist-info/LICENSE
pyfieldlib-1.0.1.dist-info/METADATA
pyfieldlib-1.0.1.dist-info/WHEEL
pyfieldlib-1.0.1.dist-info/top_level.txt
pyfieldlib-1.0.1.dist-info/RECORD
