Metadata-Version: 2.1
Name: pyfieldlib
Version: 1.0.1
Summary: Define fields simply
Home-page: https://github.com/DuelitDev/pyfieldlib
Author: DuelitDev
Author-email: jyoon07dev@gmail.com
Maintainer: DuelitDev
Maintainer-email: jyoon07dev@gmail.com
Keywords: field,fields,pyfield,pyfields,pyfieldlib
Classifier: License :: OSI Approved :: MIT License
Classifier: Programming Language :: Python :: 3.7
Classifier: Programming Language :: Python :: 3.8
Classifier: Programming Language :: Python :: 3.9
Classifier: Programming Language :: Python :: 3.10
Classifier: Programming Language :: Python :: 3.11
Requires-Python: >=3.7
License-File: LICENSE
